AFFIPred_cli/__init__.py
AFFIPred_cli/affipred.py
AFFIPred_cli/cli.py
affipred-0.0.2.dist-info/METADATA
affipred-0.0.2.dist-info/WHEEL
affipred-0.0.2.dist-info/entry_points.txt
affipred-0.0.2.dist-info/top_level.txt
affipred-0.0.2.dist-info/RECORD
